genpasswd2/__init__.py
genpasswd2/__main__.py
genpasswd2-2.0.2.dist-info/LICENSE
genpasswd2-2.0.2.dist-info/METADATA
genpasswd2-2.0.2.dist-info/WHEEL
genpasswd2-2.0.2.dist-info/entry_points.txt
genpasswd2-2.0.2.dist-info/top_level.txt
genpasswd2-2.0.2.dist-info/RECORD
