Metadata-Version: 2.1
Name: genpasswd2
Version: 2.0.2
Summary: Random password generator
Home-page: https://github.com/Graphity/genpasswd
Author: Graphity
Project-URL: Bug Tracker, https://github.com/Graphity/genpasswd/issues
Classifier: Programming Language :: Python :: 3
Classifier: License :: OSI Approved :: MIT License
Classifier: Operating System :: OS Independent
Requires-Python: >=3.6
License-File: LICENSE
Requires-Dist: docopt
Requires-Dist: pyperclip
